wzl/mqtt/__init__.py
wzl/mqtt/client.py
wzl/mqtt/exceptions.py
wzl/mqtt/logger.py
wzl_mqtt-2.6.1.dist-info/LICENSE
wzl_mqtt-2.6.1.dist-info/METADATA
wzl_mqtt-2.6.1.dist-info/WHEEL
wzl_mqtt-2.6.1.dist-info/top_level.txt
wzl_mqtt-2.6.1.dist-info/RECORD
