Metadata-Version: 2.1
Name: wzl-mqtt
Version: 2.6.1
Summary: Small library containing an MQTT publisher and receiver.
Home-page: https://git-ce.rwth-aachen.de/wzl-mq-public/iot/mqtt/
Author: Matthias Bodenbenner, Benjamin Montavon
Author-email: m.bodenbenner@wzl-mq.rwth-aachen.de
Project-URL: Bug Tracker, https://git-ce.rwth-aachen.de/wzl-mq-public/iot/mqtt/-/issues
Classifier: Programming Language :: Python :: 3
Classifier: License :: OSI Approved :: MIT License
Classifier: Operating System :: OS Independent
Requires-Python: >=3.6
License-File: LICENSE
Requires-Dist: paho-mqtt ~=1.5.1
